oligo_gen.py
oligo_gen-0.1.1.dist-info/METADATA
oligo_gen-0.1.1.dist-info/WHEEL
oligo_gen-0.1.1.dist-info/top_level.txt
oligo_gen-0.1.1.dist-info/RECORD
