Metadata-Version: 2.1
Name: oligo-gen
Version: 0.1.1
Summary: generate oligos from fasta
Home-page: UNKNOWN
Author: UNKNOWN
Author-email: UNKNOWN
License: UNKNOWN
Platform: UNKNOWN
Requires-Dist: biopython
